mySaavn/__init__.py
mySaavn/cli.py
mySaavn-2.dist-info/LICENSE.txt
mySaavn-2.dist-info/METADATA
mySaavn-2.dist-info/WHEEL
mySaavn-2.dist-info/entry_points.txt
mySaavn-2.dist-info/top_level.txt
mySaavn-2.dist-info/zip-safe
mySaavn-2.dist-info/RECORD
