Metadata-Version: 2.1
Name: mySaavn
Version: 2
Summary: A Minimal Client for JioSaavn
Home-page: https://github.com/neernjan1/mySaavn
Author: Neeraj Yadav
Author-email: nyadav70096@gmail.com
Classifier: License :: OSI Approved :: MIT License
Classifier: Programming Language :: Python :: 3
Classifier: Operating System :: OS Independent
License-File: LICENSE.txt
Requires-Dist: BeautifulSoup4
Requires-Dist: pyDes
Requires-Dist: requests
Requires-Dist: tqdm
Requires-Dist: mutagen
Requires-Dist: colorama
